openbb_terminal/__init__.py
openbb_terminal/account/__init__.py
openbb_terminal/account/account_controller.py
openbb_terminal/account/account_view.py
openbb_terminal/account/show_prompt.py
openbb_terminal/alternative/__init__.py
openbb_terminal/alternative/alt_controller.py
openbb_terminal/alternative/companieshouse/companieshouse_controller.py
openbb_terminal/alternative/companieshouse/companieshouse_model.py
openbb_terminal/alternative/companieshouse/companieshouse_view.py
openbb_terminal/alternative/companieshouse/company.py
openbb_terminal/alternative/companieshouse/company_doc.py
openbb_terminal/alternative/companieshouse/filing_data.py
openbb_terminal/alternative/hackernews_model.py
openbb_terminal/alternative/hackernews_view.py
openbb_terminal/alternative/oss/github_model.py
openbb_terminal/alternative/oss/github_view.py
openbb_terminal/alternative/oss/oss_controller.py
openbb_terminal/alternative/oss/runa_model.py
openbb_terminal/alternative/oss/runa_view.py
openbb_terminal/alternative/realestate/__init__.py
openbb_terminal/alternative/realestate/landRegistry_model.py
openbb_terminal/alternative/realestate/landRegistry_view.py
openbb_terminal/alternative/realestate/realestate_controller.py
openbb_terminal/base_helpers.py
openbb_terminal/common/__init__.py
openbb_terminal/common/behavioural_analysis/__init__.py
openbb_terminal/common/behavioural_analysis/finbrain_model.py
openbb_terminal/common/behavioural_analysis/finbrain_view.py
openbb_terminal/common/behavioural_analysis/finnhub_model.py
openbb_terminal/common/behavioural_analysis/finnhub_view.py
openbb_terminal/common/behavioural_analysis/google_model.py
openbb_terminal/common/behavioural_analysis/google_view.py
openbb_terminal/common/behavioural_analysis/reddit_helpers.py
openbb_terminal/common/behavioural_analysis/reddit_model.py
openbb_terminal/common/behavioural_analysis/reddit_view.py
openbb_terminal/common/behavioural_analysis/stocktwits_model.py
openbb_terminal_nightly-3.2.4.dev202403140009.dist-info/LICENSE
openbb_terminal_nightly-3.2.4.dev202403140009.dist-info/METADATA
openbb_terminal_nightly-3.2.4.dev202403140009.dist-info/WHEEL
openbb_terminal_nightly-3.2.4.dev202403140009.dist-info/entry_points.txt
openbb_terminal_nightly-3.2.4.dev202403140009.dist-info/RECORD
