Metadata-Version: 2.1
Name: openbb-terminal-nightly
Version: 3.2.4.dev202403140009
Summary: Investment Research for Everyone, Anywhere.
Home-page: https://openbb.co
License: MIT
Author: OpenBB
Author-email: hello@openbb.co
Requires-Python: >=3.8, !=2.7.*, !=3.0.*, !=3.1.*, !=3.2.*, !=3.3.*, !=3.4.*, !=3.5.*, !=3.6.*, !=3.7.*, !=3.11.*, !=3.12.*
Classifier: License :: OSI Approved :: MIT License
Classifier: Programming Language :: Python :: 3
Classifier: Programming Language :: Python :: 3.9
Classifier: Programming Language :: Python :: 3.10
Provides-Extra: all
Provides-Extra: doc
Provides-Extra: forecast
Provides-Extra: installer
Provides-Extra: jupyterlab
Provides-Extra: optimization
Requires-Dist: FundamentalAnalysis (>=0.2.6,<0.3.0)
Requires-Dist: GitPython (>=3.1.17,<4.0.0)
Requires-Dist: Jinja2 (>=3.0.3,<4.0.0)
Requires-Dist: Pygments (>=2.11.2,<3.0.0)
Requires-Dist: Quandl (>=3.6.0,<4.0.0)
Requires-Dist: Riskfolio-Lib (>=3.1.1,<4.0.0) ; extra == "optimization" or extra == "all"
Requires-Dist: alpha-vantage (>=2.3.1,<3.0.0)
Requires-Dist: arch (>=5.5.0,<6.0.0)
Requires-Dist: ascii-magic (>=1.6,<2.0)
Requires-Dist: bs4 (>=0.0.1,<0.0.2)
Requires-Dist: bt (>=0.2.9,<0.3.0)
Requires-Dist: ccxt (>=4.0.33,<5.0.0)
Requires-Dist: detecta (>=0.0.5,<0.0.6)
Requires-Dist: dnspython (>=2.1.0,<3.0.0)
Requires-Dist: docstring-parser (>=0.15,<0.16) ; extra == "doc"
Requires-Dist: feedparser (>=6.0.10,<7.0.0)
Requires-Dist: ffn (==0.3.6)
Requires-Dist: financedatabase (==2.1.0)
Requires-Dist: finnhub-python (>=2.4.10,<3.0.0)
Requires-Dist: finviz (>=1.4.6,<2.0.0)
Requires-Dist: finvizfinance (==0.14.7rc1)
Requires-Dist: fred (>=3.1,<4.0)
Requires-Dist: fredapi (>=0.4.3,<0.5.0)
Requires-Dist: grpcio (>=1.51.1,<2.0.0)
Requires-Dist: holidays (>=0.14.2,<0.15.0)
Requires-Dist: html5lib (>=1.1,<2.0)
Requires-Dist: intrinio-sdk (>=6.22.2,<7.0.0)
Requires-Dist: ipympl (>=0.8.2,<0.9.0)
Requires-Dist: ipython (==8.11.0)
Requires-Dist: ipywidgets (>=8.0.2,<9.0.0)
Requires-Dist: iso8601 (>=0.1.14,<0.2.0)
Requires-Dist: jedi-language-server (>=0.40.0,<0.41.0) ; extra == "jupyterlab"
Requires-Dist: jupyter-client (==7.4.1)
Requires-Dist: jupyter-server (==1.23.6)
Requires-Dist: jupyterlab (>=3.2.4,<4.0.0)
Requires-Dist: jupyterlab-code-formatter (>=1.4.10,<2.0.0) ; extra == "jupyterlab"
Requires-Dist: jupyterlab-lsp (>=3.10.1,<4.0.0) ; extra == "jupyterlab"
Requires-Dist: jupyterlab-widgets (>=3.0.3,<4.0.0)
Requires-Dist: lightgbm (==3.3.5) ; extra == "forecast" or extra == "all"
Requires-Dist: linearmodels (>=4.25,<5.0)
Requires-Dist: matplotlib (>=3.3.3,<4.0.0)
Requires-Dist: mplfinance (>=0.12.7-alpha.7,<0.13.0)
Requires-Dist: mstarpy (>=0.0.4,<0.0.5)
Requires-Dist: nixtlats (>=0.1.11,<0.2.0)
Requires-Dist: nltk (>=3.8.1,<4.0.0)
Requires-Dist: numpy (==1.23.4)
Requires-Dist: openai-whisper (>=20230124,<20230125) ; extra == "forecast" or extra == "all"
Requires-Dist: openpyxl (>=3.0.9,<4.0.0)
Requires-Dist: packaging (>=22.0)
Requires-Dist: pandas (>=1.5.0,<2.0.0)
Requires-Dist: pandas-market-calendars (>=3.2,<3.3)
Requires-Dist: pandas-ta (>=0.3.14-beta.0,<0.4.0)
Requires-Dist: papermill (==2.4)
Requires-Dist: plotly (>=5.15.0,<6.0.0)
Requires-Dist: pmaw (>=3.0.0,<4.0.0)
Requires-Dist: posthog (>=3.0.1,<4.0.0)
Requires-Dist: praw (>=7.1.4,<8.0.0)
Requires-Dist: prompt-toolkit (>=3.0.16,<4.0.0)
Requires-Dist: protobuf (==3.20.1)
Requires-Dist: psutil (!=5.9.4)
Requires-Dist: pycoingecko (>=3.1.0,<4.0.0)
Requires-Dist: pydantic (<2)
Requires-Dist: pyinstaller (>=4.10,<5.0) ; extra == "installer"
Requires-Dist: pyrsistent (>=0.19.3,<0.20.0)
Requires-Dist: pythclient (>=0.1.2,<0.2.0)
Requires-Dist: python-binance (>=1.0.15,<2.0.0)
Requires-Dist: python-coinmarketcap (>=0.2,<0.3)
Requires-Dist: python-dotenv (>=1.0.0,<2.0.0)
Requires-Dist: python-i18n (>=0.3.9,<0.4.0)
Requires-Dist: python-jose (>=3.3.0,<4.0.0)
Requires-Dist: pytorch-lightning (==1.6.5) ; extra == "forecast" or extra == "all"
Requires-Dist: pytrends (==4.9.2)
Requires-Dist: pywry (>=0.6.1,<0.7.0)
Requires-Dist: reportlab (<4)
Requires-Dist: requests (>=2.31.0,<3.0.0)
Requires-Dist: rich (>=12.6.0,<13.0.0)
Requires-Dist: ruamel.yaml (>=0.17.21,<0.18.0)
Requires-Dist: scipy (==1.10.1)
Requires-Dist: screeninfo (>=0.6.7,<0.7.0)
Requires-Dist: seaborn (>=0.11.0,<0.12.0)
Requires-Dist: setuptools (<65.5.0)
Requires-Dist: setuptools-rust (>=1.5.2,<2.0.0) ; extra == "forecast" or extra == "all"
Requires-Dist: sparqlwrapper (>=2.0.0,<3.0.0)
Requires-Dist: squarify (>=0.4.3,<0.5.0)
Requires-Dist: statsmodels (>=0.13,<0.14)
Requires-Dist: streamlit (>=1.24.1,<2.0.0)
Requires-Dist: svglib (>=1.5.0,<2.0.0)
Requires-Dist: tokenterminal (>=1.0.1,<2.0.0)
Requires-Dist: torch (>=1.11.0,<1.12.0) ; extra == "forecast" or extra == "all"
Requires-Dist: tradingview-ta (>=3.2.3,<4.0.0)
Requires-Dist: transformers (==4.27.1) ; extra == "forecast" or extra == "all"
Requires-Dist: u8darts[torch] (==0.23.0) ; extra == "forecast" or extra == "all"
Requires-Dist: vaderSentiment (==3.3.2)
Requires-Dist: valinvest (>=0.0.2,<0.0.3)
Requires-Dist: watchdog (>=2.1.9,<3.0.0)
Requires-Dist: y-py (!=0.5.5)
Requires-Dist: yahooquery (>=2.3.0,<3.0.0)
Requires-Dist: yfinance (>=0.2.28,<0.3.0)
Requires-Dist: yt-dlp (>=2023.2.17,<2024.0.0) ; extra == "forecast" or extra == "all"
Project-URL: Documentation, https://docs.openbb.co/sdk
Project-URL: Repository, https://github.com/OpenBB-finance/OpenBBTerminal
